nodescraper/__init__.py
nodescraper/configbuilder.py
nodescraper/configregistry.py
nodescraper/constants.py
nodescraper/generictypes.py
nodescraper/pluginexecutor.py
nodescraper/pluginregistry.py
nodescraper/typeutils.py
nodescraper/utils.py
nodescraper/base/__init__.py
nodescraper/base/inbandcollectortask.py
nodescraper/base/inbanddataplugin.py
nodescraper/base/regexanalyzer.py
nodescraper/cli/__init__.py
nodescraper/cli/cli.py
nodescraper/cli/constants.py
nodescraper/cli/dynamicparserbuilder.py
nodescraper/cli/helper.py
nodescraper/cli/inputargtypes.py
nodescraper/configs/node_status.json
nodescraper/connection/__init__.py
nodescraper/connection/inband/__init__.py
nodescraper/connection/inband/inband.py
nodescraper/connection/inband/inbandlocal.py
nodescraper/connection/inband/inbandmanager.py
nodescraper/connection/inband/inbandremote.py
nodescraper/connection/inband/sshparams.py
nodescraper/enums/__init__.py
nodescraper/enums/eventcategory.py
nodescraper/enums/eventpriority.py
nodescraper/enums/executionstatus.py
nodescraper/enums/osfamily.py
nodescraper/enums/systeminteraction.py
nodescraper/enums/systemlocation.py
nodescraper/interfaces/__init__.py
nodescraper/interfaces/connectionmanager.py
nodescraper/interfaces/dataanalyzertask.py
nodescraper/interfaces/datacollectortask.py
nodescraper/interfaces/dataplugin.py
nodescraper/interfaces/plugin.py
nodescraper/interfaces/resultcollator.py
nodescraper/interfaces/task.py
nodescraper/interfaces/taskresulthook.py
nodescraper/models/__init__.py
nodescraper/models/analyzerargs.py
nodescraper/models/collectorargs.py
nodescraper/models/connectionconfig.py
nodescraper/models/datamodel.py
nodescraper/models/datapluginresult.py
nodescraper/models/event.py
nodescraper/models/pluginconfig.py
nodescraper/models/pluginresult.py
nodescraper/models/systeminfo.py
nodescraper/models/taskresult.py
nodescraper/models/timerangeargs.py
nodescraper/plugins/__init__.py
nodescraper/plugins/inband/__init__.py
amd_node_scraper-1.0.1.dist-info/LICENSE
amd_node_scraper-1.0.1.dist-info/METADATA
amd_node_scraper-1.0.1.dist-info/WHEEL
amd_node_scraper-1.0.1.dist-info/entry_points.txt
amd_node_scraper-1.0.1.dist-info/top_level.txt
amd_node_scraper-1.0.1.dist-info/RECORD
