Metadata-Version: 2.1
Name: amd-node-scraper
Version: 1.0.1
Summary: A framework for automated error detection and data collection
Project-URL: homepage, https://github.com/amd/node-scraper
Project-URL: documentation, https://github.com/amd/node-scraper
Project-URL: repository, https://github.com/amd/node-scraper
Classifier: Topic :: Software Development
Requires-Python: >=3.9
License-File: LICENSE
Requires-Dist: pydantic >=2.8.2
Requires-Dist: paramiko <4.0.0,>=3.2.0
Requires-Dist: requests
Requires-Dist: pytz
Requires-Dist: urllib3 <2.0.0,>=1.26.15
Provides-Extra: dev
Requires-Dist: build ; extra == 'dev'
Requires-Dist: black ; extra == 'dev'
Requires-Dist: pylint ; extra == 'dev'
Requires-Dist: coverage ; extra == 'dev'
Requires-Dist: twine ; extra == 'dev'
Requires-Dist: ruff ; extra == 'dev'
Requires-Dist: pre-commit ; extra == 'dev'
Requires-Dist: pytest ; extra == 'dev'
Requires-Dist: pytest-cov ; extra == 'dev'
Requires-Dist: mypy ; extra == 'dev'
